nexum/__init__.py
nexum/client.py
nexum/system/__init__.py
nexum/system/completions/__init__.py
nexum/system/completions/chat.py
nexum/system/completions/utils/__init__.py
nexum/system/completions/utils/headers.py
nexum/system/completions/utils/make.py
nexum/system/completions/utils/models.py
nexum/system/diffusion/__init__.py
nexum/system/diffusion/generator.py
nexum/system/diffusion/utils/__init__.py
nexum/system/diffusion/utils/models.py
nexum/system/diffusion/utils/objects.py
nexum/system/diffusion/utils/settings.py
nexum/utils/__init__.py
nexum/utils/webtor.py
nexum-1.0.1.dist-info/METADATA
nexum-1.0.1.dist-info/WHEEL
nexum-1.0.1.dist-info/top_level.txt
nexum-1.0.1.dist-info/RECORD
