Metadata-Version: 2.1
Name: nexum
Version: 1.0.1
Summary: easy using AI, more texting models!
Home-page: https://github.com/RedPiarOfficial/nexumAi
Author: Redpiar
Author-email: Regeonwix@gmail.com
License: UNKNOWN
Keywords: flux,ai,gemini,gpt,completions,grok,diffusion,gpt-4,qwen2,llama3,gpt-4o,gpt-4o-mini,o1-mini,deepseek-r1
Platform: UNKNOWN
Classifier: Programming Language :: Python :: 3
Classifier: License :: OSI Approved :: MIT License
Classifier: Operating System :: OS Independent
Requires-Python: >=3.9
Requires-Dist: stem==1.8.2
Requires-Dist: requests==2.27.0
Requires-Dist: bs4
